{
    "WH_hww" : {
        "QQ2HQQ_FWDH"                                  : ["1.00992334491" , "1.00080789456"], 
        "QQ2HQQ_0J"                                    : ["0.974430387572", "1.04231273848"], 
        "QQ2HQQ_1J"                                    : ["0.980302966386", "1.02910685752"], 
        "QQ2HQQ_GE2J_MJJ_0_60"                         : ["0.996331026221", "1.00413883087"],
        "QQ2HQQ_GE2J_MJJ_60_120"                       : ["0.992742397704", "1.00805893423"], 
        "QQ2HQQ_GE2J_MJJ_120_350"                      : ["1.06350934503" , "0.948524096302"], 
        "QQ2HQQ_GE2J_MJJ_350_700_PTH_0_200_PTHJJ_0_25" : ["1.14700762541" , "0.908542063986"], 
        "QQ2HQQ_GE2J_MJJ_350_700_PTH_0_200_PTHJJ_GT25" : ["1.14105367192" , "0.909909137323"], 
        "QQ2HQQ_GE2J_MJJ_GT700_PTH_0_200_PTHJJ_0_25"   : ["1.1981570853"  , "0.889794183054"], 
        "QQ2HQQ_GE2J_MJJ_GT700_PTH_0_200_PTHJJ_GT25"   : ["1.18326739065" , "0.893045308272"], 
        "QQ2HQQ_GE2J_MJJ_GT350_PTH_GT200"              : ["1.09152399946" , "0.918390435823"], 
        "QQ2HLNU_FWDH"                                 : ["1.0126592563"  , "0.99940181136"], 
        "QQ2HLNU_PTV_0_75"                             : ["1.00371807406" , "1.01372564189"], 
        "QQ2HLNU_PTV_75_150"                           : ["1.00794844649" , "0.999716769274"], 
        "QQ2HLNU_PTV_150_250_0J"                       : ["0.990340799247", "1.01215042886"], 
        "QQ2HLNU_PTV_150_250_GE1J"                     : ["1.04657042517" , "0.950052598001"], 
        "QQ2HLNU_PTV_GT250"                            : ["1.00558104618" , "0.97188843247"] 
    },
    "ZH_hww" : {
        "QQ2HQQ_FWDH"                                  : ["0.99196461617" , "0.998641148153"], 
        "QQ2HQQ_0J"                                    : ["0.966654976768", "1.04536085042"], 
        "QQ2HQQ_1J"                                    : ["0.974131563065", "1.03307765408"], 
        "QQ2HQQ_GE2J_MJJ_0_60"                         : ["0.992816378476", "1.004506099"], 
        "QQ2HQQ_GE2J_MJJ_60_120"                       : ["0.985664236576", "1.01163281437"], 
        "QQ2HQQ_GE2J_MJJ_120_350"                      : ["1.06460097902" , "0.948710527155"], 
        "QQ2HQQ_GE2J_MJJ_350_700_PTH_0_200_PTHJJ_0_25" : ["1.14889058146" , "0.907054122135"], 
        "QQ2HQQ_GE2J_MJJ_350_700_PTH_0_200_PTHJJ_GT25" : ["1.1603136562"  , "0.900416001138"], 
        "QQ2HQQ_GE2J_MJJ_GT700_PTH_0_200_PTHJJ_0_25"   : ["1.26400858874" , "0.860058829124"], 
        "QQ2HQQ_GE2J_MJJ_GT700_PTH_0_200_PTHJJ_GT25"   : ["1.27115850911" , "0.856992984826"], 
        "QQ2HQQ_GE2J_MJJ_GT350_PTH_GT200"              : ["1.11552439506" , "0.908717286205"], 
        "QQ2HLL_FWDH"                                  : ["0.993115633911", "1.00204734182"],
        "QQ2HLL_PTV_0_75"                              : ["1.00194760921" , "1.01304610803"], 
        "QQ2HLL_PTV_75_150"                            : ["1.00522821384" , "0.999014977335"], 
        "QQ2HLL_PTV_150_250_0J"                        : ["0.954131398527", "1.02059134355"], 
        "QQ2HLL_PTV_150_250_GE1J"                      : ["1.05228128335" , "0.947876655366"], 
        "QQ2HLL_PTV_GT250"                             : ["0.998742845734", "0.971616703247"] 
    },
    "ggZH_hww" : {
        "GG2HLL_FWDH"            : ["1.30014457829", "0.782589229609"], 
        "GG2HLL_PTV_0_75"        : ["1.25176059272", "0.80895707711"], 
        "GG2HLL_PTV_75_150"      : ["1.26123339115", "0.80434714663"], 
        "GG2HLL_PTV_150_250_0J"  : ["1.28222701705", "0.792360236258"],
        "GG2HLL_PTV_150_250_GE1J": ["1.27592760003", "0.795437322764"], 
        "GG2HLL_PTV_GT250"       : ["1.30045183082", "0.782985021074"]
    },
    "ttH_hww" : {
        "TTH_FWDH"        : ["1.42355970553", "0.799166412588"], 
        "TTH_PTH_0_60"    : ["1.43922472807", "0.788760469357"], 
        "TTH_PTH_60_120"  : ["1.46801609792", "0.804824651649"],
        "TTH_PTH_120_200" : ["1.43265642716", "0.785640256709"], 
        "TTH_PTH_200_300" : ["1.46471249072", "0.801600636052"], 
        "TTH_PTH_GT300"   : ["1.46414288687", "0.788678309807"] 
    },
    "WH_htt" : {
        "QQ2HQQ_FWDH"                                  : ["1.01355302186" , "0.996863621042"], 
        "QQ2HQQ_0J"                                    : ["0.975040387183", "1.04241576216"], 
        "QQ2HQQ_1J"                                    : ["0.983342597876", "1.03285392613"], 
        "QQ2HQQ_GE2J_MJJ_0_60"                         : ["0.994397511161", "1.00666577102"],
        "QQ2HQQ_GE2J_MJJ_60_120"                       : ["0.994834563829", "1.0104682606"], 
        "QQ2HQQ_GE2J_MJJ_120_350"                      : ["1.0617060786"  , "0.94776658876"], 
        "QQ2HQQ_GE2J_MJJ_350_700_PTH_0_200_PTHJJ_0_25" : ["1.15082682754" , "0.907311612262"], 
        "QQ2HQQ_GE2J_MJJ_350_700_PTH_0_200_PTHJJ_GT25" : ["1.13844165397" , "0.910945053521"], 
        "QQ2HQQ_GE2J_MJJ_GT700_PTH_0_200_PTHJJ_0_25"   : ["1.20085400918" , "0.889973090741"], 
        "QQ2HQQ_GE2J_MJJ_GT700_PTH_0_200_PTHJJ_GT25"   : ["1.18045842143" , "0.894253737401"], 
        "QQ2HQQ_GE2J_MJJ_GT350_PTH_GT200"              : ["1.09011911512" , "0.918909311777"], 
        "QQ2HLNU_FWDH"                                 : ["1.0153757916"  , "0.99381016487"], 
        "QQ2HLNU_PTV_0_75"                             : ["1.00620531273" , "1.01770140063"], 
        "QQ2HLNU_PTV_75_150"                           : ["1.00526642368" , "0.999498229268"], 
        "QQ2HLNU_PTV_150_250_0J"                       : ["0.976898640226", "1.0172643377"], 
        "QQ2HLNU_PTV_150_250_GE1J"                     : ["1.04740098413" , "0.949986632644"], 
        "QQ2HLNU_PTV_GT250"                            : ["0.997139649657", "0.974930337725"] 
    },
    "ZH_htt" : {
        "QQ2HQQ_FWDH"                                  : ["0.994926030536", "0.995170983786"], 
        "QQ2HQQ_0J"                                    : ["0.96899797585" , "1.04604541705"], 
        "QQ2HQQ_1J"                                    : ["0.981247085584", "1.03981779662"], 
        "QQ2HQQ_GE2J_MJJ_0_60"                         : ["0.988830734485", "1.00505416105"], 
        "QQ2HQQ_GE2J_MJJ_60_120"                       : ["0.995947524987", "1.0244052669"], 
        "QQ2HQQ_GE2J_MJJ_120_350"                      : ["1.06084464702" , "0.945322604163"], 
        "QQ2HQQ_GE2J_MJJ_350_700_PTH_0_200_PTHJJ_0_25" : ["1.15878371344" , "0.902622875968"], 
        "QQ2HQQ_GE2J_MJJ_350_700_PTH_0_200_PTHJJ_GT25" : ["1.16112792445" , "0.899765032589"], 
        "QQ2HQQ_GE2J_MJJ_GT700_PTH_0_200_PTHJJ_0_25"   : ["1.27102684524" , "0.861565836718"], 
        "QQ2HQQ_GE2J_MJJ_GT700_PTH_0_200_PTHJJ_GT25"   : ["1.26748889594" , "0.856930358122"], 
        "QQ2HQQ_GE2J_MJJ_GT350_PTH_GT200"              : ["1.11485270134" , "0.908276300014"], 
        "QQ2HLL_FWDH"                                  : ["1.00177240135" , "1.00015183259"],
        "QQ2HLL_PTV_0_75"                              : ["0.994249075743", "1.00976039735"], 
        "QQ2HLL_PTV_75_150"                            : ["1.00204457099" , "0.996727815761"], 
        "QQ2HLL_PTV_150_250_0J"                        : ["0.974357391447", "1.01506495642"], 
        "QQ2HLL_PTV_150_250_GE1J"                      : ["1.05125842162" , "0.947685413219"], 
        "QQ2HLL_PTV_GT250"                             : ["1.00222793125" , "0.972291355477"] 
    }
}
